_kaldi_native_io.cpython-310-x86_64-linux-gnu.so
kaldi_native_io-1.22.1.data/data/bin/copy-blob
kaldi_native_io-1.22.1.dist-info/RECORD
kaldi_native_io-1.22.1.dist-info/WHEEL
kaldi_native_io-1.22.1.dist-info/LICENSE
kaldi_native_io-1.22.1.dist-info/METADATA
kaldi_native_io-1.22.1.dist-info/top_level.txt
kaldi_native_io/__init__.py
kaldi_native_io/table_types.py
kaldi_native_io/bin/copy-blob
kaldi_native_io/share/cmake/kaldi_native_io/kaldi_native_ioConfigVersion.cmake
kaldi_native_io/share/cmake/kaldi_native_io/kaldi_native_ioConfig.cmake
kaldi_native_io/include/kaldi_native_io/csrc/kaldi-utils.h
kaldi_native_io/include/kaldi_native_io/csrc/log.h
kaldi_native_io/include/kaldi_native_io/csrc/posterior.h
kaldi_native_io/include/kaldi_native_io/csrc/matrix-common.h
kaldi_native_io/include/kaldi_native_io/csrc/kaldi-io.h
kaldi_native_io/include/kaldi_native_io/csrc/kaldi-pipebuf.h
kaldi_native_io/include/kaldi_native_io/csrc/matrix-shape.h
kaldi_native_io/include/kaldi_native_io/csrc/kaldi-io-inl.h
kaldi_native_io/include/kaldi_native_io/csrc/io-funcs-inl.h
kaldi_native_io/include/kaldi_native_io/csrc/kaldi-vector.h
kaldi_native_io/include/kaldi_native_io/csrc/kaldi-semaphore.h
kaldi_native_io/include/kaldi_native_io/csrc/kaldi-holder.h
kaldi_native_io/include/kaldi_native_io/csrc/kaldi-holder-inl.h
kaldi_native_io/include/kaldi_native_io/csrc/io-funcs.h
kaldi_native_io/include/kaldi_native_io/csrc/wave-reader.h
kaldi_native_io/include/kaldi_native_io/csrc/text-utils.h
kaldi_native_io/include/kaldi_native_io/csrc/parse-options.h
kaldi_native_io/include/kaldi_native_io/csrc/kaldi-table.h
kaldi_native_io/include/kaldi_native_io/csrc/kaldi-matrix.h
kaldi_native_io/include/kaldi_native_io/csrc/compressed-matrix.h
kaldi_native_io/include/kaldi_native_io/csrc/stl-utils.h
kaldi_native_io/include/kaldi_native_io/csrc/kaldi-matrix-inl.h
kaldi_native_io/include/kaldi_native_io/csrc/kaldi-table-inl.h
kaldi_native_io/include/kaldi_native_io/csrc/basic-filebuf.h
kaldi_native_io/lib64/libkaldi_native_io_core.so
