Metadata-Version: 2.1
Name: kaldi-native-io
Version: 1.22.1
Home-page: https://github.com/csukuangfj/kaldi_native_io
Author: Fangjun Kuang
Author-email: csukuangfj@gmail.com
License: Apache licensed, as found in the LICENSE file
Classifier: Programming Language :: C++
Classifier: Programming Language :: Python
Classifier: Topic :: Scientific/Engineering :: Artificial Intelligence
License-File: LICENSE
Requires-Dist: numpy
